dup/BSTestRunner.py
dup/__init__.py
dup/__version__.py
dup/base.py
dup/case_tag.py
dup/log.py
dup/runner.py
dup/setting.py
dup/templates/template.html
dup-1.1.7.dist-info/LICENSE
dup-1.1.7.dist-info/METADATA
dup-1.1.7.dist-info/WHEEL
dup-1.1.7.dist-info/top_level.txt
dup-1.1.7.dist-info/RECORD
