Metadata-Version: 2.1
Name: dup
Version: 1.1.7
Summary: 对Python unittest的功能进行了扩展
Home-page: https://github.com/jianbing/utx
Author: jianbing
Author-email: 326333381@qq.com
License: MIT
Platform: UNKNOWN
Classifier: License :: OSI Approved :: MIT License
Classifier: Programming Language :: Python :: 2.7
Classifier: Programming Language :: Python :: Implementation :: CPython
Requires-Dist: colorama
Requires-Dist: enum34
